miya_chat/__init__.py
miya_chat/app.py
miya_chat/templates/index.html
miya_chat-0.1.17.dist-info/METADATA
miya_chat-0.1.17.dist-info/WHEEL
miya_chat-0.1.17.dist-info/entry_points.txt
miya_chat-0.1.17.dist-info/top_level.txt
miya_chat-0.1.17.dist-info/RECORD
