Metadata-Version: 2.1
Name: miya-chat
Version: 0.1.17
Summary: A simple chat application using Flask and AWS Bedrock
Home-page: 
Author: Manav Kundra
Author-email: 
Classifier: Programming Language :: Python :: 3
Classifier: License :: OSI Approved :: MIT License
Classifier: Operating System :: OS Independent
Requires-Python: >=3.6
Requires-Dist: flask
Requires-Dist: boto3
Requires-Dist: werkzeug
